pyhttpstatus_utils/__init__.py
pyhttpstatus_utils/http_status_code.py
pyhttpstatus_utils/http_status_dicts.py
pyhttpstatus_utils/http_status_enum.py
pyhttpstatus_utils/http_status_methods.py
pyhttpstatus_utils/http_status_type.py
pyhttpstatus_utils-0.3.3.dist-info/DESCRIPTION.rst
pyhttpstatus_utils-0.3.3.dist-info/METADATA
pyhttpstatus_utils-0.3.3.dist-info/RECORD
pyhttpstatus_utils-0.3.3.dist-info/WHEEL
pyhttpstatus_utils-0.3.3.dist-info/metadata.json
pyhttpstatus_utils-0.3.3.dist-info/top_level.txt
