Metadata-Version: 2.0
Name: pyhttpstatus-utils
Version: 0.3.3
Summary: Extension of Python Standard Library http.HTTPStatus providing addtional utilities.
Home-page: https://github.com/TuneLab/pyhttpstatus-utils
Author: TUNE Inc.
Author-email: jefft@tune.com
License: MIT License
Download-URL: https://github.com/TuneLab/pyhttpstatus-utils/archive/v0.3.3.tar.gz
Keywords: http httpstatus utilities tune
Platform: UNKNOWN
Classifier: Development Status :: 5 - Production/Stable
Classifier: Intended Audience :: Developers
Classifier: Operating System :: OS Independent
Classifier: Natural Language :: English
Classifier: License :: OSI Approved :: MIT License
Classifier: Programming Language :: Python
Classifier: Programming Language :: Python :: 2.7
Classifier: Programming Language :: Python :: 3.0
Classifier: Programming Language :: Python :: 3.1
Classifier: Programming Language :: Python :: 3.2
Classifier: Programming Language :: Python :: 3.3
Classifier: Programming Language :: Python :: 3.4
Classifier: Programming Language :: Python :: 3.5
Classifier: Programming Language :: Python :: 3.6
Classifier: Programming Language :: Python :: Implementation :: PyPy
Requires-Dist: httpstatus35
Requires-Dist: pprintpp (>=0.3.0)
Requires-Dist: pytest (>=3.2.5)
Requires-Dist: pytest-mock (>=1.6.3)
Requires-Dist: pytest-cov (>=2.5.1)
Requires-Dist: repoze.lru (>=0.7)
Requires-Dist: wheel (>=0.30.0)
